README.rst
setup.py
timi_uuid/__init__.py
timi_uuid/__version__.py
timi_uuid/main_uuid.py
timi_uuid.egg-info/PKG-INFO
timi_uuid.egg-info/SOURCES.txt
timi_uuid.egg-info/dependency_links.txt
timi_uuid.egg-info/top_level.txt