Metadata-Version: 1.1
Name: timi-uuid
Version: 0.0.6
Summary: A sensible class for dealing with single machine generate auto-incrementing uuid str.
Home-page: http://github.com/lxl0928/timi_uuid
Author: Timi long
Author-email: lixiaolong@smuer.cn
License: UNKNOWN
Platform: UNKNOWN
Classifier: Development Status :: 5 - Production/Stable
Classifier: Intended Audience :: Developers
Classifier: License :: OSI Approved :: BSD License
Classifier: Operating System :: OS Independent
Classifier: Programming Language :: Python
Classifier: Programming Language :: Python :: 2.6
Classifier: Programming Language :: Python :: 2.7
Classifier: Programming Language :: Python :: 3.3
Classifier: Programming Language :: Python :: 3.4
Classifier: Programming Language :: Python :: 3.5
Classifier: Programming Language :: Python :: 3.6
Classifier: Programming Language :: Python :: 3.7
